README.rst
setup.py
lispPy/Ast.py
lispPy/Error.py
lispPy/Interpreter.py
lispPy/Lexer.py
lispPy/Parser.py
lispPy/SemanticAnalyzer.py
lispPy/Token.py
lispPy/__init__.py
lispPy.egg-info/PKG-INFO
lispPy.egg-info/SOURCES.txt
lispPy.egg-info/dependency_links.txt
lispPy.egg-info/top_level.txt