Metadata-Version: 1.1
Name: lispPy
Version: 1.0.0
Summary: Toy Python Package for interpreting Lisp code, but with not as much power. Not meant for production use
Home-page: https://github.com/RachitSharma2001/Interpreter
Author: Rachit Sharma
Author-email: rachitsharma613@gmail.com
License: BSD 2-clause
Platform: UNKNOWN
Classifier: Development Status :: 1 - Planning
Classifier: Intended Audience :: Science/Research
Classifier: License :: OSI Approved :: BSD License
Classifier: Operating System :: POSIX :: Linux
Classifier: Programming Language :: Python :: 2
Classifier: Programming Language :: Python :: 2.7
Classifier: Programming Language :: Python :: 3
Classifier: Programming Language :: Python :: 3.4
Classifier: Programming Language :: Python :: 3.5
